MANIFEST.in
README.md
setup.py
sixtrackwrap/__init__.py
sixtrackwrap/conversion.py
sixtrackwrap/sixtracklib_wrap.py
sixtrackwrap.egg-info/PKG-INFO
sixtrackwrap.egg-info/SOURCES.txt
sixtrackwrap.egg-info/dependency_links.txt
sixtrackwrap.egg-info/requires.txt
sixtrackwrap.egg-info/top_level.txt
sixtrackwrap/data/beam_elements.bin
test/test.py
test/test2.py
test/test3.py