Metadata-Version: 1.0
Name: sixtrackwrap
Version: 0.0.2
Summary: basic sixtracklib for my personal needs
Home-page: UNKNOWN
Author: Carlo Emilio Montanari
Author-email: carlidel95@gmail.com
License: MIT
Platform: UNKNOWN
